{
    "optimal_time": 63.0,
    "opt_compute_time:": 0.027398070320487022,
    "spt_time": 72,
    "spt_compute_time": 1.0787478666752577,
    "lpt_time": 70,
    "lpt_compute_time": 1.3817423302680254,
    "n_jobs": 6,
    "n_resources": 6,
    "n_ops_per_job": 6,
    "max_op_time": 11,
    "jssp_identification": "6x6_2184_inst.json",
    "solution_optimality": "OPTIMAL",
    "jssp_instance": {
        "durations": [
            [
                4,
                2,
                2,
                1,
                4,
                10
            ],
            [
                10,
                1,
                11,
                11,
                11,
                9
            ],
            [
                8,
                4,
                1,
                9,
                1,
                9
            ],
            [
                6,
                11,
                7,
                11,
                11,
                3
            ],
            [
                4,
                10,
                7,
                8,
                1,
                7
            ],
            [
                4,
                3,
                9,
                8,
                3,
                7
            ]
        ],
        "machines": [
            [
                1,
                0,
                2,
                4,
                5,
                3
            ],
            [
                2,
                1,
                5,
                0,
                3,
                4
            ],
            [
                1,
                4,
                3,
                2,
                5,
                0
            ],
            [
                2,
                0,
                4,
                1,
                3,
                5
            ],
            [
                4,
                3,
                1,
                5,
                0,
                2
            ],
            [
                3,
                4,
                5,
                0,
                2,
                1
            ]
        ]
    }
}