{
    "optimal_time": 85.0,
    "opt_compute_time:": 0.07047105114907026,
    "spt_time": 98,
    "spt_compute_time": 2.59078662795946,
    "lpt_time": 108,
    "lpt_compute_time": 2.5841229860670865,
    "n_jobs": 8,
    "n_resources": 8,
    "n_ops_per_job": 8,
    "max_op_time": 11,
    "jssp_identification": "8x8_2344_inst.json",
    "solution_optimality": "OPTIMAL",
    "jssp_instance": {
        "durations": [
            [
                6,
                8,
                1,
                2,
                6,
                3,
                8,
                6
            ],
            [
                9,
                9,
                2,
                9,
                2,
                6,
                7,
                9
            ],
            [
                6,
                2,
                9,
                10,
                10,
                6,
                10,
                11
            ],
            [
                6,
                10,
                4,
                8,
                8,
                5,
                3,
                11
            ],
            [
                10,
                6,
                7,
                9,
                2,
                6,
                8,
                2
            ],
            [
                3,
                11,
                5,
                4,
                8,
                6,
                9,
                4
            ],
            [
                11,
                11,
                6,
                8,
                6,
                9,
                4,
                8
            ],
            [
                2,
                2,
                6,
                11,
                1,
                2,
                7,
                10
            ]
        ],
        "machines": [
            [
                6,
                4,
                5,
                0,
                7,
                1,
                3,
                2
            ],
            [
                6,
                4,
                0,
                3,
                2,
                7,
                5,
                1
            ],
            [
                5,
                4,
                3,
                7,
                1,
                6,
                0,
                2
            ],
            [
                2,
                7,
                5,
                3,
                6,
                1,
                4,
                0
            ],
            [
                2,
                4,
                1,
                0,
                6,
                5,
                7,
                3
            ],
            [
                3,
                6,
                4,
                0,
                5,
                2,
                7,
                1
            ],
            [
                4,
                7,
                6,
                0,
                2,
                5,
                1,
                3
            ],
            [
                5,
                0,
                4,
                7,
                6,
                1,
                3,
                2
            ]
        ]
    }
}