{
    "optimal_time": 81.0,
    "opt_compute_time:": 0.05284333322197199,
    "spt_time": 102,
    "spt_compute_time": 2.4205982140265405,
    "lpt_time": 114,
    "lpt_compute_time": 2.667343208566308,
    "n_jobs": 8,
    "n_resources": 8,
    "n_ops_per_job": 8,
    "max_op_time": 11,
    "jssp_identification": "8x8_2183_inst.json",
    "solution_optimality": "OPTIMAL",
    "jssp_instance": {
        "durations": [
            [
                11,
                8,
                2,
                8,
                4,
                5,
                3,
                6
            ],
            [
                6,
                1,
                8,
                2,
                11,
                5,
                11,
                11
            ],
            [
                8,
                9,
                4,
                3,
                4,
                3,
                11,
                9
            ],
            [
                4,
                4,
                5,
                5,
                5,
                3,
                7,
                9
            ],
            [
                10,
                4,
                9,
                6,
                2,
                8,
                1,
                5
            ],
            [
                6,
                11,
                6,
                1,
                11,
                2,
                10,
                6
            ],
            [
                5,
                9,
                5,
                8,
                10,
                1,
                11,
                11
            ],
            [
                4,
                5,
                7,
                11,
                7,
                8,
                10,
                4
            ]
        ],
        "machines": [
            [
                5,
                7,
                0,
                3,
                6,
                1,
                4,
                2
            ],
            [
                3,
                0,
                6,
                2,
                5,
                7,
                1,
                4
            ],
            [
                6,
                1,
                7,
                5,
                4,
                0,
                2,
                3
            ],
            [
                0,
                7,
                2,
                1,
                6,
                5,
                4,
                3
            ],
            [
                4,
                6,
                7,
                2,
                3,
                5,
                1,
                0
            ],
            [
                7,
                5,
                1,
                6,
                4,
                3,
                0,
                2
            ],
            [
                3,
                4,
                1,
                7,
                2,
                6,
                0,
                5
            ],
            [
                6,
                7,
                1,
                3,
                4,
                0,
                2,
                5
            ]
        ]
    }
}