{
    "optimal_time": 74.0,
    "opt_compute_time:": 0.0435538268648088,
    "spt_time": 84,
    "spt_compute_time": 1.980883790180087,
    "lpt_time": 87,
    "lpt_compute_time": 2.160401619039476,
    "n_jobs": 8,
    "n_resources": 8,
    "n_ops_per_job": 8,
    "max_op_time": 11,
    "jssp_identification": "8x8_446_inst.json",
    "solution_optimality": "OPTIMAL",
    "jssp_instance": {
        "durations": [
            [
                3,
                11,
                7,
                6,
                1,
                7,
                4,
                3
            ],
            [
                7,
                3,
                7,
                10,
                6,
                4,
                5,
                1
            ],
            [
                1,
                11,
                10,
                1,
                11,
                9,
                6,
                8
            ],
            [
                8,
                8,
                1,
                8,
                1,
                5,
                8,
                5
            ],
            [
                8,
                8,
                1,
                5,
                2,
                1,
                4,
                1
            ],
            [
                10,
                7,
                2,
                3,
                2,
                11,
                2,
                8
            ],
            [
                9,
                11,
                3,
                5,
                10,
                2,
                9,
                3
            ],
            [
                7,
                9,
                3,
                7,
                10,
                11,
                6,
                2
            ]
        ],
        "machines": [
            [
                6,
                7,
                5,
                1,
                2,
                3,
                4,
                0
            ],
            [
                5,
                4,
                2,
                6,
                3,
                1,
                0,
                7
            ],
            [
                0,
                2,
                4,
                6,
                5,
                1,
                3,
                7
            ],
            [
                3,
                2,
                4,
                1,
                7,
                5,
                6,
                0
            ],
            [
                5,
                4,
                2,
                7,
                1,
                6,
                0,
                3
            ],
            [
                1,
                0,
                5,
                2,
                7,
                3,
                4,
                6
            ],
            [
                1,
                7,
                0,
                5,
                4,
                3,
                2,
                6
            ],
            [
                2,
                1,
                7,
                0,
                4,
                6,
                3,
                5
            ]
        ]
    }
}