{
    "optimal_time": 81.0,
    "opt_compute_time:": 0.06180412881076336,
    "spt_time": 86,
    "spt_compute_time": 2.517833277117461,
    "lpt_time": 104,
    "lpt_compute_time": 2.7065971451811492,
    "n_jobs": 8,
    "n_resources": 8,
    "n_ops_per_job": 8,
    "max_op_time": 11,
    "jssp_identification": "8x8_3017_inst.json",
    "solution_optimality": "OPTIMAL",
    "jssp_instance": {
        "durations": [
            [
                3,
                1,
                1,
                9,
                1,
                3,
                7,
                3
            ],
            [
                9,
                8,
                8,
                7,
                2,
                11,
                1,
                6
            ],
            [
                8,
                8,
                7,
                11,
                11,
                4,
                5,
                9
            ],
            [
                6,
                3,
                2,
                8,
                6,
                9,
                3,
                11
            ],
            [
                9,
                9,
                10,
                8,
                5,
                10,
                5,
                6
            ],
            [
                4,
                9,
                3,
                7,
                1,
                5,
                8,
                3
            ],
            [
                5,
                9,
                6,
                7,
                4,
                11,
                4,
                5
            ],
            [
                9,
                10,
                5,
                9,
                5,
                10,
                9,
                8
            ]
        ],
        "machines": [
            [
                1,
                4,
                5,
                6,
                3,
                0,
                2,
                7
            ],
            [
                3,
                5,
                0,
                7,
                6,
                2,
                1,
                4
            ],
            [
                3,
                5,
                7,
                4,
                6,
                2,
                0,
                1
            ],
            [
                5,
                2,
                4,
                6,
                1,
                0,
                3,
                7
            ],
            [
                1,
                4,
                2,
                0,
                5,
                3,
                6,
                7
            ],
            [
                1,
                3,
                7,
                6,
                4,
                2,
                5,
                0
            ],
            [
                4,
                0,
                6,
                5,
                7,
                3,
                1,
                2
            ],
            [
                4,
                1,
                6,
                7,
                3,
                0,
                5,
                2
            ]
        ]
    }
}