{
    "optimal_time": 459.0,
    "opt_compute_time:": 0.019141582772135735,
    "spt_time": 572,
    "spt_compute_time": 8.739900910295546,
    "lpt_time": 611,
    "lpt_compute_time": 10.727921440266073,
    "n_jobs": 6,
    "n_resources": 6,
    "n_ops_per_job": 6,
    "max_op_time": 99,
    "jssp_identification": "6x6_1958_inst.json",
    "solution_optimality": "OPTIMAL",
    "jssp_instance": {
        "durations": [
            [
                15,
                53,
                14,
                60,
                52,
                10
            ],
            [
                29,
                71,
                52,
                30,
                36,
                40
            ],
            [
                27,
                60,
                37,
                63,
                71,
                80
            ],
            [
                36,
                54,
                89,
                93,
                51,
                25
            ],
            [
                6,
                26,
                71,
                62,
                33,
                19
            ],
            [
                17,
                76,
                64,
                37,
                33,
                34
            ]
        ],
        "machines": [
            [
                5,
                4,
                3,
                2,
                0,
                1
            ],
            [
                0,
                3,
                5,
                4,
                2,
                1
            ],
            [
                4,
                2,
                5,
                0,
                1,
                3
            ],
            [
                3,
                2,
                1,
                0,
                5,
                4
            ],
            [
                3,
                1,
                0,
                5,
                4,
                2
            ],
            [
                3,
                2,
                0,
                1,
                4,
                5
            ]
        ]
    }
}