{
    "optimal_time": 546.0,
    "opt_compute_time:": 0.04400088731199503,
    "spt_time": 666,
    "spt_compute_time": 13.847032045014203,
    "lpt_time": 636,
    "lpt_compute_time": 13.893268904648721,
    "n_jobs": 6,
    "n_resources": 6,
    "n_ops_per_job": 6,
    "max_op_time": 99,
    "jssp_identification": "6x6_235_inst.json",
    "solution_optimality": "OPTIMAL",
    "jssp_instance": {
        "durations": [
            [
                22,
                56,
                52,
                75,
                73,
                37
            ],
            [
                92,
                23,
                28,
                72,
                59,
                92
            ],
            [
                74,
                87,
                29,
                71,
                48,
                92
            ],
            [
                23,
                69,
                23,
                71,
                42,
                62
            ],
            [
                91,
                93,
                27,
                40,
                89,
                90
            ],
            [
                38,
                18,
                91,
                34,
                79,
                81
            ]
        ],
        "machines": [
            [
                2,
                4,
                5,
                1,
                0,
                3
            ],
            [
                0,
                4,
                1,
                3,
                2,
                5
            ],
            [
                2,
                5,
                4,
                3,
                0,
                1
            ],
            [
                1,
                0,
                3,
                2,
                5,
                4
            ],
            [
                2,
                4,
                0,
                3,
                5,
                1
            ],
            [
                0,
                5,
                1,
                2,
                4,
                3
            ]
        ]
    }
}