{
    "optimal_time": 1328.0,
    "opt_compute_time:": 2623.5360982082784,
    "spt_time": 1649,
    "spt_compute_time": 70.91056071128696,
    "lpt_time": 1946,
    "lpt_compute_time": 80.00343387760222,
    "n_jobs": 15,
    "n_resources": 15,
    "n_ops_per_job": 15,
    "max_op_time": 99,
    "jssp_identification": "15x15_77_inst.json",
    "solution_optimality": "OPTIMAL",
    "jssp_instance": {
        "durations": [
            [
                74,
                37,
                30,
                94,
                82,
                17,
                35,
                23,
                75,
                70,
                22,
                89,
                95,
                94,
                24
            ],
            [
                63,
                64,
                46,
                41,
                28,
                17,
                78,
                56,
                90,
                19,
                93,
                90,
                20,
                90,
                17
            ],
            [
                71,
                21,
                54,
                31,
                51,
                93,
                89,
                73,
                42,
                15,
                96,
                82,
                31,
                52,
                40
            ],
            [
                83,
                89,
                57,
                53,
                90,
                28,
                38,
                58,
                28,
                73,
                42,
                94,
                36,
                35,
                52
            ],
            [
                15,
                80,
                71,
                88,
                61,
                81,
                88,
                31,
                17,
                96,
                56,
                37,
                81,
                60,
                54
            ],
            [
                29,
                34,
                84,
                88,
                28,
                74,
                72,
                59,
                67,
                72,
                23,
                80,
                84,
                93,
                96
            ],
            [
                34,
                67,
                36,
                64,
                25,
                59,
                47,
                24,
                66,
                91,
                87,
                29,
                66,
                79,
                39
            ],
            [
                71,
                59,
                19,
                34,
                65,
                28,
                59,
                78,
                55,
                69,
                81,
                84,
                56,
                45,
                81
            ],
            [
                72,
                69,
                41,
                43,
                33,
                79,
                63,
                87,
                16,
                57,
                86,
                93,
                69,
                58,
                68
            ],
            [
                22,
                17,
                93,
                19,
                93,
                44,
                29,
                63,
                80,
                83,
                76,
                30,
                73,
                77,
                57
            ],
            [
                50,
                55,
                68,
                31,
                98,
                72,
                47,
                15,
                32,
                53,
                46,
                44,
                95,
                32,
                96
            ],
            [
                51,
                61,
                76,
                27,
                46,
                89,
                78,
                23,
                52,
                85,
                59,
                33,
                90,
                33,
                40
            ],
            [
                28,
                94,
                48,
                48,
                75,
                92,
                78,
                86,
                50,
                98,
                35,
                17,
                86,
                81,
                83
            ],
            [
                27,
                56,
                21,
                15,
                49,
                53,
                53,
                50,
                53,
                92,
                46,
                41,
                96,
                87,
                54
            ],
            [
                49,
                15,
                38,
                73,
                29,
                43,
                63,
                59,
                48,
                44,
                92,
                66,
                18,
                27,
                20
            ]
        ],
        "machines": [
            [
                1,
                3,
                7,
                2,
                10,
                14,
                9,
                4,
                0,
                6,
                13,
                5,
                8,
                12,
                11
            ],
            [
                1,
                8,
                0,
                13,
                11,
                3,
                14,
                2,
                4,
                5,
                10,
                7,
                12,
                6,
                9
            ],
            [
                1,
                2,
                0,
                7,
                14,
                12,
                11,
                10,
                9,
                4,
                13,
                8,
                5,
                3,
                6
            ],
            [
                13,
                7,
                14,
                9,
                4,
                11,
                12,
                1,
                8,
                0,
                2,
                5,
                6,
                3,
                10
            ],
            [
                6,
                14,
                10,
                13,
                9,
                8,
                5,
                12,
                2,
                4,
                7,
                11,
                1,
                0,
                3
            ],
            [
                13,
                11,
                14,
                3,
                12,
                10,
                0,
                7,
                1,
                4,
                6,
                8,
                5,
                2,
                9
            ],
            [
                13,
                9,
                1,
                8,
                7,
                11,
                14,
                5,
                2,
                6,
                10,
                12,
                4,
                0,
                3
            ],
            [
                3,
                8,
                7,
                9,
                10,
                2,
                12,
                6,
                1,
                13,
                14,
                0,
                11,
                5,
                4
            ],
            [
                2,
                3,
                0,
                4,
                8,
                12,
                6,
                5,
                14,
                7,
                10,
                9,
                11,
                13,
                1
            ],
            [
                1,
                14,
                12,
                13,
                2,
                10,
                7,
                9,
                0,
                3,
                5,
                8,
                6,
                4,
                11
            ],
            [
                9,
                14,
                1,
                11,
                7,
                2,
                12,
                6,
                8,
                5,
                0,
                10,
                3,
                4,
                13
            ],
            [
                1,
                4,
                14,
                7,
                10,
                6,
                11,
                8,
                0,
                9,
                2,
                3,
                12,
                5,
                13
            ],
            [
                2,
                5,
                0,
                7,
                12,
                8,
                14,
                11,
                9,
                13,
                10,
                1,
                3,
                4,
                6
            ],
            [
                1,
                2,
                7,
                10,
                11,
                12,
                13,
                4,
                8,
                9,
                6,
                0,
                14,
                3,
                5
            ],
            [
                14,
                6,
                7,
                2,
                12,
                0,
                4,
                5,
                3,
                10,
                1,
                13,
                11,
                9,
                8
            ]
        ]
    }
}