{
    "optimal_time": 1324.0,
    "opt_compute_time:": 232.6672098338604,
    "spt_time": 1647,
    "spt_compute_time": 71.07341863308102,
    "lpt_time": 1790,
    "lpt_compute_time": 74.46988450270146,
    "n_jobs": 15,
    "n_resources": 15,
    "n_ops_per_job": 15,
    "max_op_time": 99,
    "jssp_identification": "15x15_784_inst.json",
    "solution_optimality": "OPTIMAL",
    "jssp_instance": {
        "durations": [
            [
                35,
                40,
                92,
                95,
                93,
                67,
                38,
                16,
                62,
                25,
                24,
                91,
                40,
                62,
                28
            ],
            [
                92,
                78,
                36,
                90,
                32,
                79,
                40,
                81,
                22,
                70,
                48,
                37,
                83,
                69,
                74
            ],
            [
                72,
                93,
                21,
                81,
                59,
                30,
                48,
                97,
                21,
                69,
                46,
                85,
                62,
                70,
                63
            ],
            [
                32,
                44,
                40,
                22,
                49,
                93,
                32,
                22,
                33,
                31,
                81,
                36,
                62,
                70,
                84
            ],
            [
                59,
                36,
                73,
                57,
                31,
                70,
                39,
                46,
                64,
                25,
                30,
                76,
                19,
                49,
                94
            ],
            [
                54,
                95,
                40,
                21,
                30,
                51,
                16,
                95,
                27,
                92,
                95,
                21,
                61,
                60,
                70
            ],
            [
                54,
                45,
                59,
                49,
                21,
                79,
                85,
                98,
                40,
                67,
                50,
                85,
                77,
                38,
                27
            ],
            [
                31,
                95,
                74,
                50,
                59,
                32,
                72,
                72,
                54,
                97,
                59,
                67,
                86,
                77,
                96
            ],
            [
                30,
                56,
                42,
                50,
                88,
                35,
                27,
                23,
                96,
                78,
                51,
                87,
                59,
                59,
                38
            ],
            [
                88,
                44,
                49,
                19,
                19,
                76,
                35,
                86,
                29,
                90,
                44,
                22,
                24,
                90,
                15
            ],
            [
                93,
                16,
                95,
                93,
                53,
                39,
                73,
                55,
                43,
                69,
                18,
                53,
                97,
                25,
                28
            ],
            [
                71,
                80,
                27,
                61,
                39,
                71,
                38,
                52,
                83,
                54,
                15,
                91,
                35,
                19,
                81
            ],
            [
                56,
                84,
                84,
                23,
                75,
                70,
                39,
                20,
                82,
                38,
                87,
                16,
                20,
                90,
                34
            ],
            [
                26,
                84,
                91,
                31,
                64,
                90,
                53,
                70,
                21,
                64,
                92,
                63,
                63,
                70,
                28
            ],
            [
                43,
                27,
                40,
                91,
                77,
                86,
                28,
                82,
                69,
                51,
                96,
                52,
                79,
                63,
                18
            ]
        ],
        "machines": [
            [
                11,
                2,
                4,
                9,
                13,
                8,
                10,
                5,
                0,
                3,
                1,
                6,
                14,
                12,
                7
            ],
            [
                6,
                4,
                14,
                11,
                12,
                9,
                7,
                10,
                13,
                3,
                5,
                8,
                0,
                2,
                1
            ],
            [
                14,
                7,
                3,
                10,
                13,
                2,
                0,
                4,
                11,
                8,
                6,
                5,
                9,
                1,
                12
            ],
            [
                10,
                1,
                9,
                8,
                14,
                11,
                6,
                0,
                12,
                3,
                5,
                2,
                4,
                7,
                13
            ],
            [
                5,
                6,
                8,
                10,
                12,
                3,
                0,
                11,
                7,
                13,
                9,
                2,
                14,
                1,
                4
            ],
            [
                8,
                11,
                9,
                5,
                14,
                3,
                0,
                13,
                10,
                4,
                6,
                1,
                2,
                12,
                7
            ],
            [
                2,
                1,
                4,
                13,
                0,
                11,
                6,
                9,
                12,
                8,
                7,
                14,
                3,
                5,
                10
            ],
            [
                9,
                2,
                11,
                5,
                7,
                12,
                1,
                6,
                3,
                13,
                0,
                10,
                8,
                14,
                4
            ],
            [
                11,
                2,
                1,
                5,
                8,
                14,
                3,
                0,
                4,
                6,
                9,
                7,
                12,
                13,
                10
            ],
            [
                1,
                11,
                0,
                6,
                10,
                8,
                13,
                4,
                5,
                9,
                14,
                3,
                7,
                2,
                12
            ],
            [
                10,
                14,
                4,
                9,
                7,
                6,
                0,
                2,
                3,
                11,
                12,
                13,
                8,
                5,
                1
            ],
            [
                4,
                11,
                7,
                0,
                3,
                9,
                1,
                2,
                12,
                14,
                8,
                10,
                5,
                6,
                13
            ],
            [
                2,
                12,
                1,
                4,
                9,
                5,
                7,
                11,
                10,
                6,
                3,
                13,
                14,
                0,
                8
            ],
            [
                14,
                4,
                7,
                1,
                6,
                3,
                13,
                10,
                11,
                0,
                2,
                5,
                12,
                8,
                9
            ],
            [
                10,
                3,
                2,
                6,
                1,
                8,
                11,
                14,
                9,
                0,
                5,
                12,
                13,
                4,
                7
            ]
        ]
    }
}