{
    "optimal_time": 1271.0,
    "opt_compute_time:": 1158.1468476960436,
    "spt_time": 1537,
    "spt_compute_time": 61.07172033190727,
    "lpt_time": 1915,
    "lpt_compute_time": 73.08644807338715,
    "n_jobs": 15,
    "n_resources": 15,
    "n_ops_per_job": 15,
    "max_op_time": 99,
    "jssp_identification": "15x15_274_inst.json",
    "solution_optimality": "OPTIMAL",
    "jssp_instance": {
        "durations": [
            [
                61,
                53,
                35,
                17,
                40,
                79,
                68,
                20,
                17,
                50,
                31,
                86,
                30,
                47,
                55
            ],
            [
                41,
                40,
                29,
                84,
                19,
                30,
                85,
                54,
                42,
                54,
                21,
                21,
                43,
                37,
                15
            ],
            [
                30,
                69,
                92,
                38,
                62,
                58,
                31,
                95,
                93,
                25,
                65,
                64,
                58,
                52,
                72
            ],
            [
                44,
                62,
                60,
                46,
                29,
                15,
                86,
                18,
                96,
                64,
                83,
                86,
                45,
                92,
                39
            ],
            [
                64,
                94,
                62,
                79,
                37,
                89,
                37,
                40,
                93,
                43,
                26,
                72,
                74,
                89,
                27
            ],
            [
                47,
                67,
                79,
                74,
                56,
                90,
                59,
                62,
                17,
                22,
                96,
                25,
                81,
                15,
                84
            ],
            [
                76,
                84,
                43,
                90,
                35,
                21,
                88,
                36,
                55,
                90,
                82,
                90,
                34,
                31,
                70
            ],
            [
                63,
                51,
                29,
                20,
                94,
                49,
                16,
                28,
                34,
                74,
                60,
                85,
                59,
                37,
                35
            ],
            [
                85,
                20,
                26,
                30,
                93,
                61,
                68,
                38,
                17,
                23,
                79,
                67,
                79,
                98,
                59
            ],
            [
                73,
                70,
                33,
                90,
                72,
                32,
                97,
                68,
                60,
                68,
                18,
                92,
                72,
                47,
                95
            ],
            [
                98,
                88,
                18,
                23,
                57,
                74,
                69,
                67,
                60,
                77,
                34,
                66,
                71,
                91,
                23
            ],
            [
                97,
                78,
                78,
                23,
                43,
                41,
                54,
                34,
                77,
                44,
                29,
                26,
                94,
                53,
                62
            ],
            [
                86,
                75,
                71,
                21,
                36,
                47,
                90,
                57,
                98,
                18,
                53,
                15,
                38,
                83,
                38
            ],
            [
                61,
                63,
                40,
                49,
                50,
                21,
                75,
                95,
                70,
                59,
                76,
                45,
                43,
                15,
                26
            ],
            [
                73,
                44,
                60,
                93,
                33,
                67,
                66,
                75,
                80,
                25,
                47,
                49,
                45,
                69,
                48
            ]
        ],
        "machines": [
            [
                0,
                6,
                14,
                11,
                12,
                10,
                5,
                8,
                4,
                9,
                13,
                7,
                3,
                2,
                1
            ],
            [
                0,
                4,
                10,
                2,
                1,
                6,
                13,
                14,
                12,
                8,
                3,
                11,
                5,
                9,
                7
            ],
            [
                6,
                14,
                4,
                0,
                12,
                1,
                9,
                8,
                11,
                10,
                7,
                13,
                5,
                3,
                2
            ],
            [
                12,
                2,
                7,
                6,
                0,
                11,
                3,
                10,
                1,
                9,
                8,
                4,
                5,
                14,
                13
            ],
            [
                10,
                9,
                2,
                13,
                1,
                6,
                14,
                12,
                0,
                11,
                5,
                3,
                7,
                8,
                4
            ],
            [
                13,
                1,
                7,
                0,
                9,
                8,
                3,
                10,
                11,
                2,
                5,
                14,
                6,
                12,
                4
            ],
            [
                12,
                14,
                8,
                0,
                6,
                1,
                11,
                2,
                7,
                9,
                10,
                3,
                5,
                4,
                13
            ],
            [
                9,
                11,
                8,
                3,
                13,
                6,
                5,
                12,
                0,
                10,
                7,
                4,
                2,
                14,
                1
            ],
            [
                14,
                6,
                13,
                8,
                10,
                4,
                7,
                5,
                1,
                11,
                2,
                9,
                12,
                0,
                3
            ],
            [
                1,
                6,
                3,
                8,
                5,
                13,
                7,
                2,
                4,
                0,
                14,
                12,
                9,
                10,
                11
            ],
            [
                5,
                9,
                6,
                10,
                13,
                4,
                8,
                0,
                11,
                3,
                14,
                7,
                12,
                2,
                1
            ],
            [
                1,
                7,
                0,
                13,
                2,
                11,
                5,
                3,
                9,
                10,
                12,
                6,
                14,
                8,
                4
            ],
            [
                2,
                6,
                10,
                3,
                9,
                12,
                1,
                13,
                0,
                5,
                8,
                4,
                14,
                7,
                11
            ],
            [
                4,
                6,
                9,
                7,
                11,
                1,
                13,
                12,
                2,
                10,
                5,
                3,
                0,
                14,
                8
            ],
            [
                10,
                0,
                3,
                1,
                14,
                8,
                13,
                12,
                4,
                11,
                2,
                9,
                5,
                7,
                6
            ]
        ]
    }
}