{
    "optimal_time": 1352.0,
    "opt_compute_time:": 357.91426740121096,
    "spt_time": 1865,
    "spt_compute_time": 71.40956131462008,
    "lpt_time": 2000,
    "lpt_compute_time": 78.63816354237497,
    "n_jobs": 15,
    "n_resources": 15,
    "n_ops_per_job": 15,
    "max_op_time": 99,
    "jssp_identification": "15x15_407_inst.json",
    "solution_optimality": "OPTIMAL",
    "jssp_instance": {
        "durations": [
            [
                42,
                59,
                69,
                21,
                96,
                70,
                21,
                82,
                43,
                85,
                83,
                69,
                56,
                88,
                72
            ],
            [
                58,
                57,
                97,
                48,
                39,
                48,
                84,
                54,
                61,
                84,
                39,
                40,
                73,
                48,
                42
            ],
            [
                81,
                73,
                40,
                42,
                67,
                89,
                81,
                82,
                48,
                73,
                42,
                74,
                34,
                27,
                89
            ],
            [
                52,
                51,
                88,
                66,
                80,
                31,
                45,
                91,
                36,
                42,
                21,
                44,
                35,
                90,
                43
            ],
            [
                65,
                80,
                95,
                34,
                27,
                51,
                26,
                53,
                92,
                97,
                25,
                44,
                79,
                50,
                77
            ],
            [
                25,
                92,
                47,
                83,
                84,
                68,
                84,
                74,
                89,
                89,
                86,
                54,
                58,
                74,
                74
            ],
            [
                60,
                44,
                31,
                47,
                32,
                37,
                24,
                65,
                94,
                37,
                74,
                67,
                88,
                35,
                39
            ],
            [
                29,
                52,
                45,
                15,
                44,
                28,
                52,
                62,
                54,
                58,
                67,
                57,
                65,
                48,
                86
            ],
            [
                16,
                69,
                56,
                91,
                65,
                70,
                65,
                67,
                16,
                51,
                83,
                34,
                63,
                57,
                98
            ],
            [
                18,
                38,
                76,
                18,
                50,
                61,
                69,
                26,
                96,
                55,
                91,
                62,
                92,
                70,
                80
            ],
            [
                68,
                27,
                93,
                68,
                35,
                83,
                18,
                52,
                42,
                56,
                77,
                96,
                93,
                91,
                79
            ],
            [
                16,
                67,
                29,
                87,
                20,
                83,
                68,
                50,
                33,
                61,
                95,
                35,
                55,
                65,
                50
            ],
            [
                83,
                50,
                69,
                84,
                15,
                68,
                23,
                31,
                84,
                16,
                48,
                20,
                51,
                73,
                69
            ],
            [
                23,
                77,
                65,
                32,
                70,
                17,
                45,
                86,
                62,
                92,
                18,
                92,
                83,
                51,
                67
            ],
            [
                94,
                80,
                56,
                23,
                43,
                36,
                70,
                86,
                62,
                96,
                23,
                20,
                56,
                16,
                61
            ]
        ],
        "machines": [
            [
                9,
                12,
                7,
                0,
                10,
                11,
                14,
                13,
                6,
                1,
                3,
                8,
                2,
                5,
                4
            ],
            [
                14,
                12,
                2,
                7,
                3,
                5,
                6,
                1,
                0,
                10,
                9,
                11,
                8,
                4,
                13
            ],
            [
                4,
                2,
                13,
                5,
                3,
                8,
                1,
                6,
                7,
                12,
                11,
                0,
                10,
                14,
                9
            ],
            [
                0,
                6,
                10,
                3,
                13,
                4,
                12,
                9,
                2,
                7,
                5,
                1,
                11,
                8,
                14
            ],
            [
                0,
                1,
                4,
                3,
                11,
                5,
                9,
                8,
                6,
                14,
                13,
                7,
                10,
                2,
                12
            ],
            [
                10,
                12,
                7,
                14,
                8,
                11,
                9,
                3,
                1,
                4,
                5,
                13,
                2,
                0,
                6
            ],
            [
                7,
                1,
                11,
                2,
                12,
                4,
                10,
                3,
                6,
                5,
                9,
                13,
                0,
                14,
                8
            ],
            [
                4,
                5,
                7,
                1,
                9,
                14,
                11,
                6,
                2,
                3,
                13,
                12,
                10,
                8,
                0
            ],
            [
                5,
                12,
                8,
                4,
                2,
                11,
                7,
                13,
                1,
                9,
                0,
                6,
                3,
                10,
                14
            ],
            [
                1,
                14,
                8,
                10,
                3,
                9,
                11,
                0,
                5,
                7,
                12,
                4,
                2,
                13,
                6
            ],
            [
                8,
                0,
                2,
                12,
                3,
                7,
                13,
                1,
                6,
                14,
                9,
                10,
                5,
                11,
                4
            ],
            [
                12,
                9,
                3,
                7,
                5,
                8,
                0,
                4,
                14,
                10,
                1,
                11,
                2,
                6,
                13
            ],
            [
                3,
                2,
                4,
                10,
                7,
                13,
                6,
                0,
                9,
                8,
                12,
                11,
                5,
                14,
                1
            ],
            [
                5,
                2,
                9,
                14,
                6,
                8,
                10,
                11,
                1,
                4,
                7,
                0,
                12,
                13,
                3
            ],
            [
                10,
                8,
                2,
                14,
                12,
                6,
                4,
                11,
                0,
                7,
                5,
                1,
                13,
                3,
                9
            ]
        ]
    }
}